udiskie/__init__.py
udiskie/appindicator.py
udiskie/async_.py
udiskie/automount.py
udiskie/cache.py
udiskie/cli.py
udiskie/common.py
udiskie/config.py
udiskie/dbus.py
udiskie/depend.py
udiskie/locale.py
udiskie/mount.py
udiskie/notify.py
udiskie/password_dialog.ui
udiskie/prompt.py
udiskie/tray.py
udiskie/udisks2.py
udiskie/icons/__init__.py
udiskie/icons/udiskie-checkbox-checked.svg
udiskie/icons/udiskie-checkbox-unchecked.svg
udiskie/icons/udiskie-detach.svg
udiskie/icons/udiskie-eject.svg
udiskie/icons/udiskie-lock.svg
udiskie/icons/udiskie-mount.svg
udiskie/icons/udiskie-submenu.svg
udiskie/icons/udiskie-unlock.svg
udiskie/icons/udiskie-unmount.svg
udiskie-2.6.1.data/data/share/bash-completion/completions/udiskie
udiskie-2.6.1.data/data/share/bash-completion/completions/udiskie-info
udiskie-2.6.1.data/data/share/bash-completion/completions/udiskie-mount
udiskie-2.6.1.data/data/share/bash-completion/completions/udiskie-umount
udiskie-2.6.1.data/data/share/locale/de/LC_MESSAGES/udiskie.mo
udiskie-2.6.1.data/data/share/locale/en_US/LC_MESSAGES/udiskie.mo
udiskie-2.6.1.data/data/share/locale/es_ES/LC_MESSAGES/udiskie.mo
udiskie-2.6.1.data/data/share/locale/it_IT/LC_MESSAGES/udiskie.mo
udiskie-2.6.1.data/data/share/locale/ru_RU/LC_MESSAGES/udiskie.mo
udiskie-2.6.1.data/data/share/locale/sk_SK/LC_MESSAGES/udiskie.mo
udiskie-2.6.1.data/data/share/locale/tr_TR/LC_MESSAGES/udiskie.mo
udiskie-2.6.1.data/data/share/locale/zh_CN/LC_MESSAGES/udiskie.mo
udiskie-2.6.1.data/data/share/zsh/site-functions/_udiskie
udiskie-2.6.1.data/data/share/zsh/site-functions/_udiskie-canonical_paths
udiskie-2.6.1.data/data/share/zsh/site-functions/_udiskie-mount
udiskie-2.6.1.data/data/share/zsh/site-functions/_udiskie-umount
udiskie-2.6.1.dist-info/licenses/COPYING
udiskie-2.6.1.dist-info/METADATA
udiskie-2.6.1.dist-info/WHEEL
udiskie-2.6.1.dist-info/entry_points.txt
udiskie-2.6.1.dist-info/top_level.txt
udiskie-2.6.1.dist-info/RECORD
