Metadata-Version: 2.4
Name: udiskie
Version: 2.6.1
Summary: Removable disk automounter based on udisks
Author-email: Byron Clark <byron@theclarkfamily.name>, Thomas Gläßle <t_glaessle@gmx.de>
Maintainer-email: Thomas Gläßle <t_glaessle@gmx.de>
License-Expression: MIT
Project-URL: Source Code, https://github.com/coldfix/udiskie
Project-URL: Issue Tracker, https://github.com/coldfix/udiskie/issues
Project-URL: Changelog, https://github.com/coldfix/udiskie/blob/master/CHANGES.rst
Classifier: Development Status :: 5 - Production/Stable
Classifier: Environment :: Console
Classifier: Environment :: X11 Applications :: GTK
Classifier: Intended Audience :: End Users/Desktop
Classifier: Operating System :: POSIX :: Linux
Classifier: Programming Language :: Python :: 3
Classifier: Topic :: Desktop Environment
Classifier: Topic :: System :: Filesystems
Classifier: Topic :: System :: Hardware
Classifier: Topic :: Utilities
Requires-Python: >=3.5
License-File: COPYING
Requires-Dist: PyYAML
Requires-Dist: docopt
Requires-Dist: importlib_resources; python_version < "3.7"
Requires-Dist: PyGObject
Provides-Extra: password-cache
Requires-Dist: keyutils>=0.3; extra == "password-cache"
Dynamic: license-file
